example_package_dotexe3301/__init__.py
example_package_dotexe3301/colors.py
example_package_dotexe3301/dir.py
example_package_dotexe3301/fd.py
example_package_dotexe3301/inputed.py
example_package_dotexe3301/main.py
specz-1.1.0.dist-info/LICENSE.txt
specz-1.1.0.dist-info/METADATA
specz-1.1.0.dist-info/WHEEL
specz-1.1.0.dist-info/top_level.txt
specz-1.1.0.dist-info/RECORD
