Metadata-Version: 2.1
Name: specz
Version: 1.1.0
Summary: A small python package that can list a file's specification in user's terminal.
Author: Shivesh Vijay
Author-email: Shivesh Vijay <shiveshvijay707@gmail.com>
Classifier: Programming Language :: Python :: 3
Classifier: License :: OSI Approved :: MIT License
Classifier: Operating System :: OS Independent
Requires-Python: >=3.7, <4
License-File: LICENSE.txt
